{
  "last_updated": "2025-09-11T16:55:46.888377",
  "total_unique_entries": 8994,
  "daily_files": 1,
  "dictionary_files": 38,
  "entries_by_letter": {
    "ニ": {
      "words": 2,
      "definitions": 2
    },
    "C": {
      "words": 636,
      "definitions": 646
    },
    "ʻ": {
      "words": 1,
      "definitions": 1
    },
    "ツ": {
      "words": 1,
      "definitions": 1
    },
    "Т": {
      "words": 1,
      "definitions": 1
    },
    "S": {
      "words": 1039,
      "definitions": 1055
    },
    "É": {
      "words": 1,
      "definitions": 1
    },
    "O": {
      "words": 150,
      "definitions": 153
    },
    "B": {
      "words": 637,
      "definitions": 649
    },
    "V": {
      "words": 151,
      "definitions": 151
    },
    "R": {
      "words": 353,
      "definitions": 363
    },
    "T": {
      "words": 527,
      "definitions": 532
    },
    "Á": {
      "words": 1,
      "definitions": 1
    },
    "P": {
      "words": 475,
      "definitions": 483
    },
    "G": {
      "words": 384,
      "definitions": 393
    },
    "Q": {
      "words": 56,
      "definitions": 57
    },
    "M": {
      "words": 538,
      "definitions": 544
    },
    "Æ": {
      "words": 1,
      "definitions": 1
    },
    "F": {
      "words": 432,
      "definitions": 436
    },
    "E": {
      "words": 191,
      "definitions": 192
    },
    "Y": {
      "words": 113,
      "definitions": 113
    },
    "L": {
      "words": 279,
      "definitions": 288
    },
    "Z": {
      "words": 63,
      "definitions": 65
    },
    "I": {
      "words": 184,
      "definitions": 187
    },
    "X": {
      "words": 18,
      "definitions": 18
    },
    "โ": {
      "words": 1,
      "definitions": 1
    },
    "Š": {
      "words": 1,
      "definitions": 1
    },
    "Ș": {
      "words": 1,
      "definitions": 1
    },
    "OTHER": {
      "words": 123,
      "definitions": 127
    },
    "A": {
      "words": 487,
      "definitions": 495
    },
    "K": {
      "words": 248,
      "definitions": 253
    },
    "W": {
      "words": 225,
      "definitions": 230
    },
    "N": {
      "words": 303,
      "definitions": 311
    },
    "J": {
      "words": 294,
      "definitions": 305
    },
    "U": {
      "words": 78,
      "definitions": 84
    },
    "H": {
      "words": 350,
      "definitions": 356
    },
    "十": {
      "words": 1,
      "definitions": 1
    },
    "D": {
      "words": 489,
      "definitions": 496
    }
  },
  "daily_breakdown": {
    "2025-09-11": 8994
  }
}