{
  "woofsnow": [
    {
      "defid": 12800870,
      "definition": "[WHAT THE FUCK]",
      "example": "woofsnow? ([adverb]) (woofs-now)",
      "written_on": "2018-05-22T00:00:00Z"
    }
  ],
  "WOS": [
    {
      "defid": 3575818,
      "definition": "[Wife] Over [Shoulder]",
      "example": "log as from IM, blog, or e-mail to [e-cheating] [partner]:\r\n...[want to] MIRL, oops WOS, bye!",
      "written_on": "2008-12-26T00:00:00Z"
    }
  ],
  "Wac Willer": [
    {
      "defid": 6351022,
      "definition": "A [form] of [insult] or diss towards [Mac Miller].",
      "example": "Did u [hear] that Wac [Willer] song? It was most [weak].",
      "written_on": "2012-01-08T00:00:00Z"
    }
  ],
  "Wop": [
    {
      "defid": 13908224,
      "definition": "a [nicotine] machine. a term coined by the Yaris Gang of [East Bay], [California], meaning “without papers” referring to the use of tobacco.",
      "example": "(in [bathroom])\r\nGirl 1: Can I hit your whomp?\r\nGirl 2: It’s wop. But [yeah I guess]. It’s [lychee] juice",
      "written_on": "2019-05-16T00:00:00Z"
    }
  ],
  "Whole Person": [
    {
      "defid": 16806259,
      "definition": "A whole person is an [individual] whose [personality] emotionally drains you after the thought or action of [interacting] with them. While recalling your personal experience with the \"Whole Person\", you will often find yourself frustrated, angry, or confused by their actions.",
      "example": "\"Abbys aunt is two whole people\"\n\n\"Just got off the phone with my [mother-in-law]. God. She is a WHOLE PERSON\"\n\n\"I [personally] cannot handle the fact that you are being a whole person [right now]\"",
      "written_on": "2021-12-02T20:58:42.791Z"
    }
  ],
  "wikiwalking": [
    {
      "defid": 1910097,
      "definition": "(v) to follow hyperlinks through various [wikipedia] articles with no [express] [destination]",
      "example": "\"[I've been] wikiwalking since 9 o'clock! - started off in [Bangladesh] and ended up at Prime Minister's [Questions]!\"",
      "written_on": "2006-08-12T00:00:00Z"
    }
  ],
  "wyte boy": [
    {
      "defid": 2034004,
      "definition": "a [white person] that is into rap/hip hop, wears baggy clothes, talks like [ghetto people], \r\nbewteen rock [white person] and a black person but not a wigger",
      "example": "blck: [wats good] wyte boy\r\nwhte: [not much] jus chillin yo ima go igght [hit me up] latte r\r\nblck: iigth 1",
      "written_on": "2006-10-16T00:00:00Z"
    }
  ],
  "weehaahoo!": [
    {
      "defid": 17752029,
      "definition": "an [expression] used to [indicate] [immense] glee",
      "example": "“Weehaahoo!” [Ruben] [said] as he received a [stroopwafel].",
      "written_on": "2023-04-14T14:38:59.887Z"
    }
  ],
  "White Trash Cadillac": [
    {
      "defid": 5888730,
      "definition": "a police cruiser (preferably a Crown Victoria) that was bought in a police auction.\n\nThese are a real prize if they still have the spot light and cattle guard still on them.\n\nThe holy grail of [White Trash] Cadillacs is one that was an undercover police car with tinted windows and a sweet paint job.\n\nA [driving game] can be played by guessing from a distance whether a Crown Vic is an actual police car or a [White Trash] Caddy.",
      "example": "Yo Jimmy is that a [cop car] or a [White Trash] [Cadillac]?",
      "written_on": "2011-06-15T00:00:00Z"
    }
  ],
  "woah woah bud": [
    {
      "defid": 18234771,
      "definition": "A word (or, phrase that you say when ur mate says [something] [fucked up] and/or [out of pocket]. I stole this from my friend, be careful when you say this. one wrong move and boom! I'm in ur walls!",
      "example": "Billie: Dickhead Fuckface, Cock smokin, motherfuckin asshole dirty twat [waste of semen] [I hope you die]!\r\nMike: Woah woah bud, watch the swears\r\nTre: lets just make this a song, [who cares]?",
      "written_on": "2024-05-30T16:06:24.819Z"
    }
  ],
  "William": [
    {
      "defid": 10634136,
      "definition": "So... Hugo cock, [really cool] and all [the Girls] want him(and [have sex]).\n\nWilliam: Likes to FUCK ;)",
      "example": "Hi [My Name Is] William And I [Like To] [Fuck] :)",
      "written_on": "2016-12-12T08:35:11.013Z"
    }
  ],
  "whacked": [
    {
      "defid": 1127445,
      "definition": "[demented];  [not right] [in the head]",
      "example": "When [someone] says [the same] thing to you [ten times] they're whacked.",
      "written_on": "2005-05-13T00:00:00Z"
    }
  ],
  "Walden University": [
    {
      "defid": 2922917,
      "definition": "An online diploma mill [masquerading] as a school. They started as small non-accredited college selling degrees through the mail and have since graduating to sending people spam messages about their graduate programs. Everyone who applies will be accepted as they don’t require a GRE, SAT, or a pulse. If you can pay, you can [get yourself] a Walden education. \r\n\r\nTheir professors are all part-time employees who are usually employed at other colleges at teach at Walden for the [extra money]. All of their classes are canned and don’t really require any real learning. Just write papers and do the minimum and you’ll have a worthless degree in no time at all.\r\n\r\nThe people who run the small [office] in Minneapolis, MN change regularly and are usually unhappy with their lives. The school goes through deans and heads of departments so quickly that even the staff jokes about it.\r\n\r\nThis is the college for anyone who wants to brag about having a degree while they’re restocking the shelves at Target.",
      "example": "I worked at Walden [University] for two years, finished my online MBA with them, and still can’t [get a job] anywhere else. F*ck Walden [University].",
      "written_on": "2008-03-13T00:00:00Z"
    }
  ],
  "wastehoe": [
    {
      "defid": 11331813,
      "definition": "[A hoe] that's [a waste]",
      "example": "[Omg] you're [such a] wastehoe",
      "written_on": "2017-03-25T00:00:00Z"
    }
  ],
  "windy gap birds": [
    {
      "defid": 17651175,
      "definition": "[Walker] dew [scouting] for [birds] that are 15",
      "example": "there were so [many] [Windy gap] [birds] wanting me",
      "written_on": "2023-01-31T07:13:58.33Z"
    }
  ],
  "Wrii": [
    {
      "defid": 16562572,
      "definition": "Wrii refers to [good looking], wriisome, [person].\n\n(Wriisome is just like [awesome] but more fancy)",
      "example": ",,[Dude] that [streamer] is [wriisome]! Yes she's Wrii\"",
      "written_on": "2021-11-22T12:21:55.615Z"
    }
  ],
  "whime": [
    {
      "defid": 2771361,
      "definition": "[Vagina], [pussy], [Axe wound], cunt.",
      "example": "You could [drive a] Mac [truck] through that [ho's] whime!",
      "written_on": "2008-01-12T00:00:00Z"
    }
  ],
  "Wyatt bailey": [
    {
      "defid": 17631307,
      "definition": "Short, big sexy , has the coolest [overalls] , great smile, the also tend to have [beautiful] shiny [brown hair] that smells like ausie shampoo, also has the tendency to suffer shititis,\r\nTend to be more red neck and dumber than the average male",
      "example": "[That guy] [over there] is [totally] a Wyatt\n\nDamnnnnnnnn shawty is yo name wyatt Bailey?!",
      "written_on": "2023-01-16T18:46:15.889Z"
    }
  ],
  "wexlinator": [
    {
      "defid": 3312722,
      "definition": "noun. of or [pertaining] to j.wexler when shes done [something] [especially] JANTASTIC and cool",
      "example": "yo wexlinator im having a [mad] [party]!",
      "written_on": "2008-10-18T00:00:00Z"
    }
  ],
  "Wisconsiner": [
    {
      "defid": 5865745,
      "definition": "A person from [Wisconsin]. They're not a [Wisconsinite]. They're not a fucking \"Sconnie.\" Only [douchebags] and out-a-staters that go to school here call themselves \"Sconnies.\" Must be pronounced with a southeast Wisconsin yaw, i.e. \"wisz-CAHN-sinerr\"",
      "example": "[Drunk Bitch]: \"WHEW!! [SCONNIE] PRIDE [BITCHES]\"\n\nWisconsiner: \"I ain't no sconnie, I'm a muthafuckin' Wisconsiner\"",
      "written_on": "2011-11-22T00:00:00Z"
    }
  ],
  "Whizzles": [
    {
      "defid": 3632209,
      "definition": "Code for a [ecstasy] [pill](s) in [the Yay Area]",
      "example": "[Aye], you [got] any \"whizzles\"",
      "written_on": "2009-01-17T00:00:00Z"
    }
  ],
  "washcloth": [
    {
      "defid": 1497762,
      "definition": "1. a small towel, [usually] made from terrycloth, of which is used to clean one's self while bathing. can also be used to clean up after intimate [relations] whether solo or with a partner.\r\n\r\n2. term also used as to describe people and/or objects that are [desirable].\r\n\r\n3. also see: hot.",
      "example": "Dude: \"OMG, did you see that [smokin' hot] chick at the skatepark [the other day]?\"\r\n\r\nOther Dude: \"[Affirmative]! She was WAY hot... after seeing her, I need a washcloth.\"",
      "written_on": "2005-10-28T00:00:00Z"
    }
  ],
  "why did you look this word up": [
    {
      "defid": 15419886,
      "definition": "You are [literally] reading a [definition] of a [sentence] because ur bored.",
      "example": "[you are] [wasting] ur time so why [did you] look this word up",
      "written_on": "2020-10-25T17:38:13.229Z"
    }
  ],
  "weinerprick": [
    {
      "defid": 2694138,
      "definition": "[Someone] who is a [weiner] and a prick. They [accomplished] the name from not just being a weiner or a prick but both. Call somone that who is acting like a dick only worse.",
      "example": "[Your such a] weinerprick!",
      "written_on": "2007-12-16T00:00:00Z"
    }
  ],
  "Wanjack": [
    {
      "defid": 5540210,
      "definition": "Instructor at Ferris State [University]. One who is a lazy [piece of shit] bastard who lives at home with only his dog. And makes his students do work that was not taught. The instructor being five minutes late to class is early, ten to [fifteen minutes] is average, if going to be later a call is issued to a student to wait forty five minutes and class is held late.",
      "example": "My instructor hasn't been laid in [the last] [decade], [what a] wanjack.",
      "written_on": "2011-01-24T00:00:00Z"
    }
  ],
  "walking wed": [
    {
      "defid": 17330130,
      "definition": "People living empty, souless, [loveless] [mundane] [married] lives who just waited and hoped for death.",
      "example": "After knocking up his highschool [girlfriend] he was forced to to get married join [the ranks] of [the walking] wed.",
      "written_on": "2022-06-26T16:30:04.294Z"
    }
  ],
  "Witches Hats": [
    {
      "defid": 3590205,
      "definition": "What you call [womens] [nipples] when they are [poking] through their shirt.",
      "example": "Hey [Carol], your [witches] hats are [showing].",
      "written_on": "2009-01-01T00:00:00Z"
    }
  ],
  "Wepost": [
    {
      "defid": 12125834,
      "definition": "YOU [POST IT] FIRST THAN [I SEE] IT AND [POST IT] NOW ITS A #WEPOST",
      "example": "THIS [MEME] IS A WEPOST 🤔",
      "written_on": "2017-11-03T00:00:00Z"
    }
  ],
  "Water Noodle": [
    {
      "defid": 5471635,
      "definition": "[A penis] with so much [foreskin] that it [looks like] it flows like water.",
      "example": "Tim's [water] [noodle] [flowed] effortlessly out of his fly.",
      "written_on": "2010-12-29T00:00:00Z"
    }
  ],
  "wannabe slut": [
    {
      "defid": 6428759,
      "definition": "An [attractive girl] in her teens or 20's, that dresses in slutty sexy clothes [showing off] her figure and boobs, and has her hair and make up done perfect. But she is a virgin, hasn't done anything sexual and is too shy to bother talking about the subject. They are worse than women who are prick teasers, as these girls [don't even] talk with guys. Many can be found in High Schools. AVOID!!",
      "example": "Mike: Victoria is such a wannabe slut, she's sooo [smoking hot] but she's just to shy. She could be such a sex kitten if she wanted to be, but she won't even talk about it.\r\nFrank: Yeah, if a chick can't [talk the talk], why even bother to [walk the walk], lol.",
      "written_on": "2012-03-24T00:00:00Z"
    }
  ],
  "Windle": [
    {
      "defid": 18455024,
      "definition": "To [jump out] [a window]",
      "example": "Don't windle, you're [a good person]",
      "written_on": "2025-03-20T08:29:05.889Z"
    }
  ],
  "witch": [
    {
      "defid": 4281718,
      "definition": "Witch, n. A properly trained and initiated Priest or Priestess of The Old Religion. From Old English wit or wic [which means] witty, wise or [intelligent], or alternatively to bend or to shape, and related to wit, wicked, wicker, wizard.\n\nWitches learn and pass down old magical arts such as contacting departed spirits, working [the weather], and reading the signs.",
      "example": "King Sol found a witch in Endor who could [communicate] [across] the [boundary] of death.",
      "written_on": "2009-10-07T00:00:00Z"
    }
  ],
  "Wienerpuss": [
    {
      "defid": 18394985,
      "definition": "A [slang] term for [a man] that has transitioned to [female].",
      "example": "Dude, I just [found out] that she is [actually] a HE and it [turns out] he has a wienerpuss.",
      "written_on": "2024-12-22T21:40:37.458Z"
    }
  ],
  "What The Farquad": [
    {
      "defid": 4736907,
      "definition": "This is a term you say when something unbelievingly [unpredictable] happens and it is just too good to say [what the fuck]. Its origin is from [Lord Farquad] from the movie Shrek, because he is a totally unpredictable badass!",
      "example": "Oliver: (Jumped off a twenty story [building] and survived)\r\nJuan: [What the] Farquad!\r\nAndres: Isnt [that the] badass guy from shrek?",
      "written_on": "2010-02-27T00:00:00Z"
    }
  ],
  "W0EEEsplaining": [
    {
      "defid": 18080908,
      "definition": "Verb; To [advertise] a university's [amateur radio] club at an event where nobody is [interested].",
      "example": "HAM 1: What's [on the docket] for today?\r\nHAM 2: [Looks like] Radio Club is W0EEEsplaining at Sophomore Seminar.\r\nHam 1: They know nobody will [actually] join, right?",
      "written_on": "2024-01-18T10:38:33.161Z"
    }
  ],
  "woman": [
    {
      "defid": 18457599,
      "definition": "[Person] of [feminine gender] with 18 or more of [18 years] of age.",
      "example": "Woman.",
      "written_on": "2025-03-23T06:47:16.721Z"
    }
  ],
  "what color is Your Wheelchair?": [
    {
      "defid": 17591647,
      "definition": "A [question] [someone] would ask that implies that you are [disabled].",
      "example": "[You suck] at [playing basketball]!\r\nHey, what color is your [wheelchair]?",
      "written_on": "2022-12-15T21:14:17.973Z"
    }
  ],
  "Warren": [
    {
      "defid": 11230304,
      "definition": "Warren is an amazing guy with an absolutely amazing [personality]. His [girlfriend] means the world to him and he will do anything for her. His is a very sexy man with a very fat and long dick which his girlfriend loves. He's smart very athletic a great kisser and best in the bed. When he's in a [relationship] with a girl he will cry for her and make her feel like she's the world and he never cheats. He's very loyal and usually his first girlfriend will be his wife. He favorite thing is to see his girl smiling and making sure she's happy. Warren is the guy of your dreams. You can also see his dick through his pants. He is also very funny and fun to hang with.",
      "example": "Wow who is that! That's Warren he the best guy ever [just look] at his dick! Also he's very loyal to his [girlfriend] so we have [no chance], sadly.",
      "written_on": "2017-04-09T00:00:00Z"
    }
  ],
  "wao": [
    {
      "defid": 13626760,
      "definition": "[We Are One]",
      "example": "WAO, #wao, #WAO",
      "written_on": "2019-02-17T00:00:00Z"
    }
  ],
  "weather grandpa": [
    {
      "defid": 7016677,
      "definition": "(or grandma if referring to a girl): an [offensive] term for a person who is always quetching about, as the name suggests, about [the weather].\n\nN.B: this term was named based my personal observation that it's mostly old grumpy grandmas and grandpas that quetch about [the weather].",
      "example": "[everybody] hates a weather grandpa, especially when the person doing the [complaining] is under 40 of age and is driving [everyone] around them nuts.",
      "written_on": "2013-04-10T21:10:22.692Z"
    }
  ],
  "Wikiwhore": [
    {
      "defid": 2411324,
      "definition": "[Person] who uses [wikipedia] WAYYY [too much].",
      "example": "I used [wikipedia] for my [term paper]. I'm [such a] wikiwhore.",
      "written_on": "2007-05-27T00:00:00Z"
    }
  ],
  "Word": [
    {
      "defid": 15776889,
      "definition": "[Type] your [definition] here...",
      "example": "Type an [example] of how its [used] in a [sentience]...\n\nword",
      "written_on": "2021-02-26T07:39:30.044Z"
    }
  ],
  "wtfaila": [
    {
      "defid": 6235453,
      "definition": "([abb].) [What the fuck am I] [looking] at.",
      "example": "[Person 1]: *posts picture of [fat bitch] shoving a doll into her vagina*\r\n[Person 2]: wtfaila?",
      "written_on": "2011-11-26T00:00:00Z"
    }
  ],
  "wnba": [
    {
      "defid": 1360195,
      "definition": "a.k.a. Beaver Ball.\r\n[Ultra fugly] \"women\" [trying to] recreate the game of [basketball].",
      "example": "Hey man, did you [hit that] [second half] total of that beaver [ball game]?",
      "written_on": "2005-07-26T00:00:00Z"
    }
  ],
  "whack": [
    {
      "defid": 14599038,
      "definition": "[LEVI]",
      "example": "[LEVI] IS [SOO] WHACK",
      "written_on": "2020-01-03T00:00:00Z"
    }
  ],
  "Warangal": [
    {
      "defid": 16038955,
      "definition": "Warangal is a [beautiful] city in [Telangana] [State]",
      "example": "Warangal is a cultural [heritage] [site]",
      "written_on": "2021-05-28T04:36:23.362Z"
    }
  ],
  "wooperxield": [
    {
      "defid": 17687546,
      "definition": "The act of [smashing] your [nintendo] system [on the ground] when you catch a Wooper.",
      "example": "\"DAMNIT, [MY BROTHER] JUST WOOPERXIELD AND NOW [I LOST] MY [POKEMON]\"",
      "written_on": "2023-02-26T16:46:11.475Z"
    }
  ],
  "Wizzin": [
    {
      "defid": 3103525,
      "definition": "To be getting [panties in a bunch] over nothing, to be \"tripping\" [if you will].  Means that you are being really [unpleasant], uncool, and people dont want to be around you. (Verb, gerund)",
      "example": "BRO why you wizzin on me?!?!?! I [thought] that you were above elias and his wizzinness in [wizland] like a [wizzard].",
      "written_on": "2008-05-21T00:00:00Z"
    }
  ],
  "Whordiot": [
    {
      "defid": 14798419,
      "definition": "A [idiot] who’s [a whore]",
      "example": "She’[s a] [little] whordiot",
      "written_on": "2020-03-13T00:00:00Z"
    }
  ],
  "WM2B": [
    {
      "defid": 11396650,
      "definition": "W [stands] for wasn't\n\nM [stands] for meant\n\n2 [stands] for to\r\nB stands for be",
      "example": "\" [Whatever] [fuck it] because it \"WM2B\"...",
      "written_on": "2017-04-06T00:00:00Z"
    }
  ],
  "watching the wire": [
    {
      "defid": 2895398,
      "definition": "1) the act of viewing the suberb hbo show the wire\r\n\r\n2) a [euphemism] for self pleasure without wanting to say the words \"[masturbating] like peter [on the dole]\".",
      "example": "Lorcan: well i'm going on a big session of [watching] the wire so [let me know] if it needs to be [disturbed]\r\n*fap fap fap*",
      "written_on": "2008-03-02T00:00:00Z"
    }
  ],
  "Wupe": [
    {
      "defid": 15836303,
      "definition": "[Really] far away. [A time] consuming [walk].",
      "example": "Brodo- [yo man] you mind [delivering] a tre to me. I’m [out west].\n\nFam’nem- idk cuz that’s a wupe for me.",
      "written_on": "2021-03-18T10:22:37.415Z"
    }
  ]
}